pyql/__init__.py
pyql/data.py
pyql/test.py
pyql_db-2.7.dist-info/METADATA
pyql_db-2.7.dist-info/WHEEL
pyql_db-2.7.dist-info/top_level.txt
pyql_db-2.7.dist-info/RECORD
