Metadata-Version: 2.1
Name: pyql-db
Version: 2.7
Summary: Simple python database orchestration utility which makes it easy to add tables, insert, select, update, delete items with tables
Home-page: https://github.com/codemation/pyql
Author: Joshua Jamison
Author-email: joshjamison1@gmail.com
License: UNKNOWN
Platform: UNKNOWN
Classifier: Programming Language :: Python :: 3
Classifier: License :: OSI Approved :: MIT License
Classifier: Operating System :: OS Independent
Requires-Python: >=3.4, <4
Requires-Dist: mysql-connector-python
